edc_auth/__init__.py
edc_auth/admin_site.py
edc_auth/apps.py
edc_auth/backends.py
edc_auth/constants.py
edc_auth/export_users.py
edc_auth/fix_export_permissions.py
edc_auth/forms.py
edc_auth/get_app_codenames.py
edc_auth/get_clinic_codenames.py
edc_auth/import_users.py
edc_auth/model_mixins.py
edc_auth/password_setter.py
edc_auth/post_migrate_signals.py
edc_auth/send_new_credentials_to_user.py
edc_auth/site_auths.py
edc_auth/system_checks.py
edc_auth/urls.py
edc_auth/urls_for_accounts.py
edc_auth/utils.py
edc_auth/views.py
edc_auth/admin/__init__.py
edc_auth/admin/fieldsets.py
edc_auth/admin/group_admin.py
edc_auth/admin/list_filters.py
edc_auth/admin/log_entries_admin.py
edc_auth/admin/role_admin.py
edc_auth/admin/user_admin.py
edc_auth/admin/user_profile_admin.py
edc_auth/auth_objects/__init__.py
edc_auth/auth_objects/default_groups.py
edc_auth/auth_objects/default_pii_models.py
edc_auth/auth_objects/default_roles.py
edc_auth/auth_objects/codenames/__init__.py
edc_auth/auth_objects/codenames/account_manager.py
edc_auth/auth_objects/codenames/administration.py
edc_auth/auth_objects/codenames/auditor.py
edc_auth/auth_objects/codenames/celery_manager.py
edc_auth/auth_objects/codenames/clinic.py
edc_auth/auth_objects/codenames/clinic_super.py
edc_auth/auth_objects/codenames/everyone.py
edc_auth/auth_updater/__init__.py
edc_auth/auth_updater/auth_updater.py
edc_auth/auth_updater/group_updater.py
edc_auth/auth_updater/role_updater.py
edc_auth/management/commands/export_users.py
edc_auth/management/commands/fix_export_permissions.py
edc_auth/management/commands/import_users.py
edc_auth/management/commands/reset_password.py
edc_auth/management/commands/__pycache__/export_users.cpython-38.pyc
edc_auth/management/commands/__pycache__/fix_export_permissions.cpython-38.pyc
edc_auth/management/commands/__pycache__/import_users.cpython-37.pyc
edc_auth/management/commands/__pycache__/import_users.cpython-38.pyc
edc_auth-1.0.2.dist-info/licenses/AUTHORS.rst
edc_auth-1.0.2.dist-info/licenses/LICENSE
edc_auth-1.0.2.dist-info/METADATA
edc_auth-1.0.2.dist-info/WHEEL
edc_auth-1.0.2.dist-info/top_level.txt
edc_auth-1.0.2.dist-info/RECORD
